spirit_gpu/__init__.py
spirit_gpu/_version.py
spirit_gpu/concurrency.py
spirit_gpu/conf.py
spirit_gpu/env.py
spirit_gpu/handler.py
spirit_gpu/heartbeat.py
spirit_gpu/log.py
spirit_gpu/manager.py
spirit_gpu/proxy.py
spirit_gpu/server.py
spirit_gpu/settings.py
spirit_gpu/task.py
spirit_gpu/worker.py
spirit_gpu/builder/__init__.py
spirit_gpu/builder/generator.py
spirit_gpu/builder/parse.py
spirit_gpu/cmd/__init__.py
spirit_gpu/cmd/builder.py
spirit_gpu/resources/worker-template/Dockerfile
spirit_gpu/resources/worker-template/LICENSE
spirit_gpu/resources/worker-template/README.md
spirit_gpu/resources/worker-template/requirements.txt
spirit_gpu/resources/worker-template/scripts/build.sh
spirit_gpu/resources/worker-template/scripts/start.sh
spirit_gpu/resources/worker-template/src/build.py
spirit_gpu/resources/worker-template/src/main.py
spirit_gpu/utils/__init__.py
spirit_gpu/utils/file.py
spirit_gpu/utils/validate.py
spirit_gpu-0.1.0.dist-info/LICENSE
spirit_gpu-0.1.0.dist-info/METADATA
spirit_gpu-0.1.0.dist-info/WHEEL
spirit_gpu-0.1.0.dist-info/entry_points.txt
spirit_gpu-0.1.0.dist-info/top_level.txt
spirit_gpu-0.1.0.dist-info/RECORD
