Metadata-Version: 2.1
Name: spirit-gpu
Version: 0.1.0
Summary: Python serverless framework for Datastone Spirit GPU.
Home-page: https://github.com/datastone-spirit
Author: spirit
Author-email: Spirit <pypi@datastone.cn>
License: MIT License
Project-URL: Homepage, https://github.com/datastone-spirit
Project-URL: Documentation, https://github.com/datastone-spirit/spirit-gpu/blob/main/README.md
Project-URL: Repository, https://github.com/datastone-spirit/spirit-gpu
Project-URL: BugTracker, https://github.com/datastone-spirit/spirit-gpu/issues
Keywords: serverless,ai,gpu,machine learning,SDK,library,python,API
Classifier: Topic :: Software Development :: Libraries :: Application Frameworks
Classifier: License :: OSI Approved :: MIT License
Classifier: Programming Language :: Python :: 3.9
Classifier: Operating System :: OS Independent
Classifier: Environment :: GPU
Requires-Python: >=3.9
License-File: LICENSE
Requires-Dist: requests>=2.31.0
Requires-Dist: PyYAML>=6.0.1
Requires-Dist: backoff>=2.2.1
Requires-Dist: aiohttp>=3.9.1
Requires-Dist: pydantic>=2.5.2
Requires-Dist: datamodel-code-generator>=0.26.3
Requires-Dist: dacite>=1.8.0
Provides-Extra: test
Requires-Dist: pytest; extra == "test"
